installer/__init__.py
installer/apps/__init__.py
installer/apps/cli.py
installer/apps/click.py
installer/apps/constants.py
installer/apps/download.py
installer/apps/lib.py
installer/cli.py
installer/click.py
installer/clone/__init__.py
installer/clone/cli.py
installer/clone/constants.py
installer/clone/lib.py
installer/configs/__init__.py
installer/configs/cli.py
installer/configs/click.py
installer/configs/constants.py
installer/configs/lib.py
installer/py.typed
installer/types.py
installer/utilities.py
dycw_installer-0.7.15.dist-info/WHEEL
dycw_installer-0.7.15.dist-info/entry_points.txt
dycw_installer-0.7.15.dist-info/METADATA
dycw_installer-0.7.15.dist-info/RECORD
