Metadata-Version: 2.3
Name: dycw-installer
Version: 0.7.15
Summary: Installer
Author: Derek Wan
Author-email: Derek Wan <d.wan@icloud.com>
Requires-Dist: click>=8.3.1
Requires-Dist: dycw-utilities>=0.188.12
Requires-Dist: inflect>=7.5.0
Requires-Dist: pydantic>=2.12.5
Requires-Dist: pygithub>=2.8.1
Requires-Dist: shellingham>=1.5.4
Requires-Dist: click==8.3.1 ; extra == 'cli'
Requires-Dist: dycw-utilities==0.188.12 ; extra == 'cli'
Requires-Dist: inflect==7.5.0 ; extra == 'cli'
Requires-Dist: pydantic==2.12.5 ; extra == 'cli'
Requires-Dist: pygithub==2.8.1 ; extra == 'cli'
Requires-Dist: shellingham==1.5.4 ; extra == 'cli'
Requires-Python: >=3.12
Provides-Extra: cli
